<PlusConfiguration version="2.0">

  <DataCollection StartupDelaySec="1.0">
    <DeviceSet 
      Name="SonixRP L14-5 + NDI Certus" 
      Description="Configuration file for SonixRP L14-5 + NDI Certus + fCal 1.0
The computer needs to be on the same local network as SonixTOUCH and the Certus SCU unit. The tools need to be plugged in the slots as following: 1: Probe, 2: Reference, 3: Stylus, 4: Needle (optional)"
    />

    <Device
      Id="TrackerDevice"
      Type="CertusTracker"
      AcquisitionRate="50"
      LocalTimeOffsetSec="0.0" >
      <Tool Name="Probe" PortName="0" Model="L14-5_38" BufferSize="2500" AveragedItemsForFiltering="20"/>
      <Tool Name="Reference" PortName="1" BufferSize="2500" AveragedItemsForFiltering="20"/>
      <Tool Name="Stylus" PortName="2" Model="Example" BufferSize="2500" AveragedItemsForFiltering="20"/>
      <Tool Name="Needle" PortName="3" Model="Example" BufferSize="2500" AveragedItemsForFiltering="20"/>
      
      <OutputStream Id="TrackerOutput" >
        <Tool Name="Probe"/>
        <Tool Name="Reference"/>
        <Tool Name="Stylus"/>
        <Tool Name="Needle"/>
      </OutputStream>
    </Device>

    <Device
      Id="VideoDevice"
      Type="SonixVideo" 
      UsImageOrientation="UF"
      AcquisitionRate="30" 
      LocalTimeOffsetSec="-0.2976"
      IP="130.15.7.20" 
      ImagingMode="BMode"
      AcquisitionDataType="BPost" 
      Depth="-1" 
      Sector="-1" 
      Gain="-1" 
      DynRange="-1" 
      Zoom="-1" 
      Frequency="-1" 
      Timeout="-1" 
      CompressionStatus="0" >
      <Image Id="VideoOutput" BufferSize="500" AveragedItemsForFiltering="20" />
      <OutputStream Id="VideoDeviceOutput">
        <Image Id="VideoOutput"/>
      </OutputStream>
    </Device>

    <Device Id="FinalMixer" Type="VirtualStreamMixer" Selectable="True">
      <OutputStream Id="Final"/>
      <InputStream Id="TrackerOutput" />
      <InputStream Id="VideoDeviceOutput" />
    </Device>
  </DataCollection>


  <CoordinateDefinitions>
    <Transform From="Image" To="TransducerOriginPixel"
      Matrix="1 0 0 -320
              0 1 0 5
              0 0 1 0
              0 0 0 1"
      Date="2011.12.07 11:39:00" Error="0.0"
    />    
  </CoordinateDefinitions> 


  <Rendering WorldCoordinateFrame="Reference">
    <DisplayableObject Type="Model" ObjectCoordinateFrame="TransducerOrigin" Id="ProbeModel"
      File="L14-5_38_ProbeModel.stl"
      ModelToObjectTransform="
        -1 0 0 29.7
        0 -1 0 1.5
        0 0 1 -14
        0 0 0 1"
    />
  <DisplayableObject Type="Model" ObjectCoordinateFrame="Reference" Id="Volume"/>
    <DisplayableObject Type="Model" ObjectCoordinateFrame="StylusTip" Id="StylusModel"
      File="Stylus_Example.stl"
      ModelToObjectTransform="
        1 0 0 -210.0
        0 1 0 0
        0 0 1 0
        0 0 0 1"
    />
    <DisplayableObject Id="PhantomModel" Type="Model" ObjectCoordinateFrame="Phantom"
      Opacity="0.6"
      File="FCal_1.0.stl"
      ModelToObjectTransform="
        1 0 0 -15.0
        0 1 0 10.0
        0 0 1 -5.0
        0 0 0 1"
      />
    <DisplayableObject Type="Image" ObjectCoordinateFrame="Image" Id="LiveImage"/>
  </Rendering>


  <Segmentation
    ApproximateSpacingMmPerPixel="0.098"
    MorphologicalOpeningCircleRadiusMm="0.55"
    MorphologicalOpeningBarSizeMm="2.0"
    RegionOfInterest="25 25 615 455"
    MaxLinePairDistanceErrorPercent="10.0"
    MaxAngleDifferenceDegrees="11"
    MinThetaDegrees="-70"
    MaxThetaDegrees="70"
    AngleToleranceDegrees="10"
    ThresholdImagePercent="10.0"
    CollinearPointsMaxDistanceFromLineMm="0.52"
    UseOriginalImageIntensityForDotIntensityScore="0"
  />


  <PhantomDefinition>
    <!-- Supported types are: Double-N, U-Shaped-N -->
    <Description
      Name="fCAL"
      Type="Double-N"
      Version="1.0"
      WiringVersion="1.0"
      Institution="Queen's University PerkLab"
    />

    <Geometry>
      <Pattern Type="NWire">
        <Wire Name="1:E3_e3" EndPointFront="20.0 0.0 5.0" EndPointBack="20.0 40.0 5.0" />
        <Wire Name="2:F3_j3" EndPointFront="25.0 0.0 5.0" EndPointBack="45.0 40.0 5.0" />
        <Wire Name="3:K3_k3" EndPointFront="50.0 0.0 5.0" EndPointBack="50.0 40.0 5.0" />
      </Pattern>
      <Pattern Type="NWire">
        <Wire Name="4:E4_e4" EndPointFront="20.0 0.0 0.0" EndPointBack="20.0 40.0 0.0" />
        <Wire Name="5:J4_f4" EndPointFront="45.0 0.0 0.0" EndPointBack="25.0 40.0 0.0" />
        <Wire Name="6:K4_k4" EndPointFront="50.0 0.0 0.0" EndPointBack="50.0 40.0 0.0" />
      </Pattern>

      <Landmarks>
        <Landmark Name="#1" Position="95.0 5.0 15.0" />
        <Landmark Name="#2" Position="95.0 40.0 15.0" />
        <Landmark Name="#3" Position="95.0 40.0 0.0" />
        <Landmark Name="#4" Position="95.0 0.0 0.0" />

        <Landmark Name="#5" Position="-25.0 40.0 15.0" />
        <Landmark Name="#6" Position="-25.0 0.0 10.0" />
        <Landmark Name="#7" Position="-25.0 0.0 0.0" />
        <Landmark Name="#8" Position="-25.0 40.0 0.0" />
      </Landmarks>
    </Geometry>
  </PhantomDefinition>


  <VolumeReconstruction OutputSpacing="0.5 0.5 0.5"
    ClipRectangleOrigin="0 0" ClipRectangleSize="820 616"
    Interpolation="LINEAR" Optimization="FULL" Compounding="On" FillHoles="Off"
  />


  <fCal
    PhantomModelId="PhantomModel"
    ReconstructedVolumeId="Volume"
    TransducerModelId="ProbeModel"
    StylusModelId="StylusModel"
    ImageDisplayableObjectId="LiveImage"
    NumberOfCalibrationImagesToAcquire="200"
    NumberOfValidationImagesToAcquire="100"
    NumberOfStylusCalibrationPointsToAcquire="200"
    RecordingIntervalMs="100"
    MaxTimeSpentWithProcessingMs="70"
    ImageCoordinateFrame="Image"
    ProbeCoordinateFrame="Probe"
    ReferenceCoordinateFrame="Reference"
    TransducerOriginCoordinateFrame="TransducerOrigin"
    TransducerOriginPixelCoordinateFrame="TransducerOriginPixel"
    TemporalCalibrationDurationSec="10"
  />


  <vtkPivotCalibrationAlgo
    ObjectMarkerCoordinateFrame="Stylus"
    ReferenceCoordinateFrame="Reference"
    ObjectPivotPointCoordinateFrame="StylusTip"
  />


  <vtkPhantomRegistrationAlgo
    PhantomCoordinateFrame="Phantom"
    ReferenceCoordinateFrame="Reference"
    StylusTipCoordinateFrame="StylusTip"
  />


  <vtkProbeCalibrationAlgo
    ImageCoordinateFrame="Image"
    ProbeCoordinateFrame="Probe"
    PhantomCoordinateFrame="Phantom"
    ReferenceCoordinateFrame="Reference"
  />

</PlusConfiguration>